ds_toolkit/__init__.py
ds_toolkit/log/__init__.py
ds_toolkit/log/allowed_context.py
ds_toolkit/log/context_logger_adapter.py
ds_toolkit/log/fmt.py
ds_toolkit/log/json_encoders.py
ds_toolkit/log/validate_context.py
ds_cc_toolkit-0.1.4.dist-info/METADATA
ds_cc_toolkit-0.1.4.dist-info/WHEEL
ds_cc_toolkit-0.1.4.dist-info/entry_points.txt
ds_cc_toolkit-0.1.4.dist-info/RECORD
