Metadata-Version: 2.3
Name: ds-cc-toolkit
Version: 0.1.4
Summary: A collection of resources to be used by the Data Science Services
Author: lukasbenicCC
Author-email: lukas@cloudcycle.com
Requires-Python: >=3.11,<4.0
Classifier: Programming Language :: Python :: 3
Classifier: Programming Language :: Python :: 3.11
Classifier: Programming Language :: Python :: 3.12
Classifier: Programming Language :: Python :: 3.13
